ilonimi/__init__.py
ilonimi/kana.py
ilonimi/lukin.py
ilonimi/main.py
ilonimi/tunimi.py
ilonimi/ud.py
ilonimi/util.py
ilonimi/wannimi.py
ilonimi/modules/__init__.py
ilonimi/modules/detokenizer.py
ilonimi/modules/joiner.py
ilonimi/modules/kanaizer.py
ilonimi/modules/normalizer.py
ilonimi/modules/proper.py
ilonimi/modules/split_kana.py
ilonimi/modules/splitter.py
ilonimi/modules/tokenizer.py
ilonimi/vocab/__init__.py
ilonimi/vocab/vocabulary.py
ilonimi/vocab/vocabulary.txt
ilonimi-1.5.0.dist-info/METADATA
ilonimi-1.5.0.dist-info/WHEEL
ilonimi-1.5.0.dist-info/entry_points.txt
ilonimi-1.5.0.dist-info/top_level.txt
ilonimi-1.5.0.dist-info/RECORD
