Metadata-Version: 2.1
Name: ilonimi
Version: 1.5.0
Summary: Toki Pona Tokenizer / Detokenizer / Kanaizer
Home-page: https://github.com/nymwa/ilonimi
Author: nymwa
Author-email: nymwa0@gmail.com
Classifier: Programming Language :: Python :: 3.8
Classifier: License :: OSI Approved :: MIT License
Classifier: Operating System :: OS Independent
